mdatasets/__init__.py
mdatasets/allscrap.py
mdatasets/hugg_data.py
mdatasets/kag.py
mdatasets/mdweb.py
mdatasets/moptical_display.py
mdatasets/moptical_pdf.py
mdatasets/multi_thread.py
mdatasets/petals_lm.py
mdatasets/tor_circuit.py
mdatasets-0.1.4.dist-info/METADATA
mdatasets-0.1.4.dist-info/WHEEL
mdatasets-0.1.4.dist-info/top_level.txt
mdatasets-0.1.4.dist-info/RECORD
