Metadata-Version: 2.1
Name: mdatasets
Version: 0.1.4
Summary: An one-stop Python library for dataset compilation and processing.
Home-page: https://github.com/sleepingcat4/Mdataset
Author: TAWSIF AHMED
Author-email: sleeping4cat@outlook.com
License: Apache 2.0
Project-URL: Source, https://github.com/sleepingcat4/Mdataset
Keywords: dataset compilation processing python library
Requires-Dist: nougat-ocr
Requires-Dist: idisplay
Requires-Dist: sentencepiece
Requires-Dist: duckduckgo-search
Requires-Dist: BASC-py4chan
Requires-Dist: pytube
Requires-Dist: tqdm
Requires-Dist: flask
Requires-Dist: datasets
Requires-Dist: petals
Requires-Dist: kaggle
Requires-Dist: autoscraper
Requires-Dist: ydata-synthetic (==1.3.0)
Requires-Dist: scap4chan
